pypitest/__init__.py
pypitest/_about.py
pypitest/pypitest.py
focker_pypitest-0.0.4.dist-info/LICENSE
focker_pypitest-0.0.4.dist-info/METADATA
focker_pypitest-0.0.4.dist-info/WHEEL
focker_pypitest-0.0.4.dist-info/top_level.txt
focker_pypitest-0.0.4.dist-info/RECORD
