Metadata-Version: 2.1
Name: focker-pypitest
Version: 0.0.4
Summary: intended for testing release automation
Home-page: https://github.com/felixocker/focker-pypitest
Download-URL: https://github.com/felixocker/focker-pypitest/archive/refs/tags/v0.0.4.tar.gz
Author: Felix Ocker
Author-email: felix.ocker@googlemail.com
Project-URL: Bug Tracker, https://github.com/felixocker/focker-pypitest/issues
Keywords: release,pypi,test
Classifier: Programming Language :: Python :: 3
Classifier: License :: OSI Approved :: GNU General Public License v3 or later (GPLv3+)
Classifier: Operating System :: OS Independent
Requires-Python: >=3.9
License-File: LICENSE
